{"meta": {"version": 1, "request": "http://nba.cloud/games/0020501175/boxscoretraditional?Format=json", "time": "2025-02-17T15:33:05.335Z"}, "boxScoreTraditional": {"gameId": "0020501175", "awayTeamId": 1610612753, "homeTeamId": 1610612759, "homeTeam": {"teamId": 1610612759, "teamCity": "San Antonio", "teamName": "Spurs", "teamTricode": "SAS", "teamSlug": "spurs", "players": [{"personId": 1477, "firstName": "Bruce", "familyName": "Bowen", "nameI": "B. Bowen", "playerSlug": "bruce-bowen", "position": "F", "comment": "", "jerseyNum": "", "statistics": {"minutes": "34:41", "fieldGoalsMade": 1, "fieldGoalsAttempted": 2, "fieldGoalsPercentage": 0.5, "threePointersMade": 1, "threePointersAttempted": 2, "threePointersPercentage": 0.5, "freeThrowsMade": 0, "freeThrowsAttempted": 0, "freeThrowsPercentage": 0.0, "reboundsOffensive": 0, "reboundsDefensive": 3, "reboundsTotal": 3, "assists": 1, "steals": 0, "blocks": 0, "turnovers": 1, "foulsPersonal": 1, "points": 3, "plusMinusPoints": -2.0}}, {"personId": 1495, "firstName": "Tim", "familyName": "Duncan", "nameI": "T. Duncan", "playerSlug": "tim-duncan", "position": "F", "comment": "", "jerseyNum": "", "statistics": {"minutes": "37:35", "fieldGoalsMade": 12, "fieldGoalsAttempted": 19, "fieldGoalsPercentage": 0.632, "threePointersMade": 0, "threePointersAttempted": 0, "threePointersPercentage": 0.0, "freeThrowsMade": 7, "freeThrowsAttempted": 10, "freeThrowsPercentage": 0.7, "reboundsOffensive": 1, "reboundsDefensive": 12, "reboundsTotal": 13, "assists": 6, "steals": 2, "blocks": 2, "turnovers": 5, "foulsPersonal": 3, "points": 31, "plusMinusPoints": -3.0}}, {"personId": 1737, "firstName": "Nazr", "familyName": "Mohammed", "nameI": "N. Mohammed", "playerSlug": "nazr-mohammed", "position": "C", "comment": "", "jerseyNum": "", "statistics": {"minutes": "15:42", "fieldGoalsMade": 1, "fieldGoalsAttempted": 3, "fieldGoalsPercentage": 0.333, "threePointersMade": 0, "threePointersAttempted": 0, "threePointersPercentage": 0.0, "freeThrowsMade": 0, "freeThrowsAttempted": 2, "freeThrowsPercentage": 0.0, "reboundsOffensive": 0, "reboundsDefensive": 2, "reboundsTotal": 2, "assists": 1, "steals": 0, "blocks": 0, "turnovers": 1, "foulsPersonal": 2, "points": 2, "plusMinusPoints": -9.0}}, {"personId": 2225, "firstName": "Tony", "familyName": "Parker", "nameI": "T. Parker", "playerSlug": "tony-parker", "position": "G", "comment": "", "jerseyNum": "", "statistics": {"minutes": "25:49", "fieldGoalsMade": 6, "fieldGoalsAttempted": 11, "fieldGoalsPercentage": 0.545, "threePointersMade": 0, "threePointersAttempted": 0, "threePointersPercentage": 0.0, "freeThrowsMade": 0, "freeThrowsAttempted": 0, "freeThrowsPercentage": 0.0, "reboundsOffensive": 2, "reboundsDefensive": 2, "reboundsTotal": 4, "assists": 4, "steals": 1, "blocks": 0, "turnovers": 7, "foulsPersonal": 2, "points": 12, "plusMinusPoints": 4.0}}, {"personId": 699, "firstName": "Brent", "familyName": "Barry", "nameI": "B. Barry", "playerSlug": "brent-barry", "position": "G", "comment": "", "jerseyNum": "", "statistics": {"minutes": "25:17", "fieldGoalsMade": 2, "fieldGoalsAttempted": 11, "fieldGoalsPercentage": 0.182, "threePointersMade": 1, "threePointersAttempted": 4, "threePointersPercentage": 0.25, "freeThrowsMade": 0, "freeThrowsAttempted": 1, "freeThrowsPercentage": 0.0, "reboundsOffensive": 1, "reboundsDefensive": 3, "reboundsTotal": 4, "assists": 5, "steals": 0, "blocks": 0, "turnovers": 1, "foulsPersonal": 1, "points": 5, "plusMinusPoints": -7.0}}, {"personId": 1725, "firstName": "Rasho", "familyName": "Nesterovic", "nameI": "R. Nesterovic", "playerSlug": "rasho-nesterovic", "position": "G", "comment": "", "jerseyNum": "", "statistics": {"minutes": "22:30", "fieldGoalsMade": 1, "fieldGoalsAttempted": 3, "fieldGoalsPercentage": 0.333, "threePointersMade": 0, "threePointersAttempted": 0, "threePointersPercentage": 0.0, "freeThrowsMade": 0, "freeThrowsAttempted": 0, "freeThrowsPercentage": 0.0, "reboundsOffensive": 2, "reboundsDefensive": 3, "reboundsTotal": 5, "assists": 0, "steals": 0, "blocks": 0, "turnovers": 0, "foulsPersonal": 3, "points": 2, "plusMinusPoints": -4.0}}, {"personId": 714, "firstName": "Michael", "familyName": "Finley", "nameI": "M. Finley", "playerSlug": "michael-finley", "position": "G", "comment": "", "jerseyNum": "", "statistics": {"minutes": "36:02", "fieldGoalsMade": 6, "fieldGoalsAttempted": 10, "fieldGoalsPercentage": 0.6, "threePointersMade": 2, "threePointersAttempted": 4, "threePointersPercentage": 0.5, "freeThrowsMade": 2, "freeThrowsAttempted": 3, "freeThrowsPercentage": 0.667, "reboundsOffensive": 1, "reboundsDefensive": 3, "reboundsTotal": 4, "assists": 2, "steals": 2, "blocks": 1, "turnovers": 0, "foulsPersonal": 2, "points": 16, "plusMinusPoints": -15.0}}, {"personId": 89, "firstName": "Nick", "familyName": "Van Exel", "nameI": "N. Van Exel", "playerSlug": "nick-van-exel", "position": "F", "comment": "", "jerseyNum": "", "statistics": {"minutes": "16:34", "fieldGoalsMade": 0, "fieldGoalsAttempted": 3, "fieldGoalsPercentage": 0.0, "threePointersMade": 0, "threePointersAttempted": 1, "threePointersPercentage": 0.0, "freeThrowsMade": 0, "freeThrowsAttempted": 0, "freeThrowsPercentage": 0.0, "reboundsOffensive": 1, "reboundsDefensive": 0, "reboundsTotal": 1, "assists": 2, "steals": 1, "blocks": 0, "turnovers": 0, "foulsPersonal": 0, "points": 0, "plusMinusPoints": -9.0}}, {"personId": 109, "firstName": "Robert", "familyName": "Horry", "nameI": "R. Horry", "playerSlug": "robert-horry", "position": "G", "comment": "", "jerseyNum": "", "statistics": {"minutes": "19:11", "fieldGoalsMade": 4, "fieldGoalsAttempted": 9, "fieldGoalsPercentage": 0.444, "threePointersMade": 1, "threePointersAttempted": 3, "threePointersPercentage": 0.333, "freeThrowsMade": 0, "freeThrowsAttempted": 0, "freeThrowsPercentage": 0.0, "reboundsOffensive": 3, "reboundsDefensive": 3, "reboundsTotal": 6, "assists": 1, "steals": 0, "blocks": 2, "turnovers": 0, "foulsPersonal": 3, "points": 9, "plusMinusPoints": -6.0}}, {"personId": 2757, "firstName": "Beno", "familyName": "Udrih", "nameI": "B. Udrih", "playerSlug": "beno-udrih", "position": "", "comment": "", "jerseyNum": "", "statistics": {"minutes": "5:37", "fieldGoalsMade": 0, "fieldGoalsAttempted": 2, "fieldGoalsPercentage": 0.0, "threePointersMade": 0, "threePointersAttempted": 0, "threePointersPercentage": 0.0, "freeThrowsMade": 0, "freeThrowsAttempted": 0, "freeThrowsPercentage": 0.0, "reboundsOffensive": 0, "reboundsDefensive": 0, "reboundsTotal": 0, "assists": 0, "steals": 0, "blocks": 0, "turnovers": 1, "foulsPersonal": 0, "points": 0, "plusMinusPoints": -7.0}}, {"personId": 101177, "firstName": "Fabricio", "familyName": "Oberto", "nameI": "F. Oberto", "playerSlug": "fabricio-oberto", "position": "", "comment": "", "jerseyNum": "", "statistics": {"minutes": "1:02", "fieldGoalsMade": 0, "fieldGoalsAttempted": 0, "fieldGoalsPercentage": 0.0, "threePointersMade": 0, "threePointersAttempted": 0, "threePointersPercentage": 0.0, "freeThrowsMade": 0, "freeThrowsAttempted": 0, "freeThrowsPercentage": 0.0, "reboundsOffensive": 0, "reboundsDefensive": 0, "reboundsTotal": 0, "assists": 0, "steals": 0, "blocks": 0, "turnovers": 0, "foulsPersonal": 0, "points": 0, "plusMinusPoints": -2.0}}, {"personId": 1938, "firstName": "Manu", "familyName": "Ginobili", "nameI": "M. Ginobili", "playerSlug": "manu-ginobili", "position": "", "comment": "DNP - Coach's Decision", "jerseyNum": "", "statistics": {"minutes": "", "fieldGoalsMade": 0, "fieldGoalsAttempted": 0, "fieldGoalsPercentage": 0.0, "threePointersMade": 0, "threePointersAttempted": 0, "threePointersPercentage": 0.0, "freeThrowsMade": 0, "freeThrowsAttempted": 0, "freeThrowsPercentage": 0.0, "reboundsOffensive": 0, "reboundsDefensive": 0, "reboundsTotal": 0, "assists": 0, "steals": 0, "blocks": 0, "turnovers": 0, "foulsPersonal": 0, "points": 0, "plusMinusPoints": 0.0}}], "statistics": {"minutes": "240:00", "fieldGoalsMade": 33, "fieldGoalsAttempted": 73, "fieldGoalsPercentage": 0.452, "threePointersMade": 5, "threePointersAttempted": 14, "threePointersPercentage": 0.357, "freeThrowsMade": 9, "freeThrowsAttempted": 16, "freeThrowsPercentage": 0.563, "reboundsOffensive": 11, "reboundsDefensive": 31, "reboundsTotal": 42, "assists": 22, "steals": 6, "blocks": 5, "turnovers": 16, "foulsPersonal": 17, "points": 80, "plusMinusPoints": -12.0}, "starters": {"minutes": "139:04", "fieldGoalsMade": 22, "fieldGoalsAttempted": 46, "fieldGoalsPercentage": 0.478, "threePointersMade": 2, "threePointersAttempted": 6, "threePointersPercentage": 0.333, "freeThrowsMade": 7, "freeThrowsAttempted": 13, "freeThrowsPercentage": 0.538, "reboundsOffensive": 4, "reboundsDefensive": 22, "reboundsTotal": 26, "assists": 17, "steals": 3, "blocks": 2, "turnovers": 15, "foulsPersonal": 9, "points": 53}, "bench": {"minutes": "139:04", "fieldGoalsMade": 11, "fieldGoalsAttempted": 27, "fieldGoalsPercentage": 0.407, "threePointersMade": 3, "threePointersAttempted": 8, "threePointersPercentage": 0.375, "freeThrowsMade": 2, "freeThrowsAttempted": 3, "freeThrowsPercentage": 0.667, "reboundsOffensive": 7, "reboundsDefensive": 9, "reboundsTotal": 16, "assists": 5, "steals": 3, "blocks": 3, "turnovers": 1, "foulsPersonal": 8, "points": 27}}, "awayTeam": {"teamId": 1610612753, "teamCity": "Orlando", "teamName": "Magic", "teamTricode": "ORL", "teamSlug": "magic", "players": [{"personId": 2045, "firstName": "Hedo", "familyName": "Turkoglu", "nameI": "H. Turkoglu", "playerSlug": "hedo-turkoglu", "position": "F", "comment": "", "jerseyNum": "", "statistics": {"minutes": "35:53", "fieldGoalsMade": 6, "fieldGoalsAttempted": 11, "fieldGoalsPercentage": 0.545, "threePointersMade": 1, "threePointersAttempted": 1, "threePointersPercentage": 1.0, "freeThrowsMade": 2, "freeThrowsAttempted": 3, "freeThrowsPercentage": 0.667, "reboundsOffensive": 0, "reboundsDefensive": 4, "reboundsTotal": 4, "assists": 1, "steals": 1, "blocks": 0, "turnovers": 1, "foulsPersonal": 2, "points": 15, "plusMinusPoints": 10.0}}, {"personId": 2730, "firstName": "Dwight", "familyName": "Howard", "nameI": "D. Howard", "playerSlug": "dwight-howard", "position": "F", "comment": "", "jerseyNum": "", "statistics": {"minutes": "37:46", "fieldGoalsMade": 9, "fieldGoalsAttempted": 15, "fieldGoalsPercentage": 0.6, "threePointersMade": 0, "threePointersAttempted": 0, "threePointersPercentage": 0.0, "freeThrowsMade": 4, "freeThrowsAttempted": 7, "freeThrowsPercentage": 0.571, "reboundsOffensive": 3, "reboundsDefensive": 10, "reboundsTotal": 13, "assists": 1, "steals": 1, "blocks": 1, "turnovers": 2, "foulsPersonal": 2, "points": 22, "plusMinusPoints": 13.0}}, {"personId": 1499, "firstName": "Tony", "familyName": "Battie", "nameI": "T. Battie", "playerSlug": "tony-battie", "position": "G", "comment": "", "jerseyNum": "", "statistics": {"minutes": "30:37", "fieldGoalsMade": 3, "fieldGoalsAttempted": 9, "fieldGoalsPercentage": 0.333, "threePointersMade": 0, "threePointersAttempted": 0, "threePointersPercentage": 0.0, "freeThrowsMade": 0, "freeThrowsAttempted": 0, "freeThrowsPercentage": 0.0, "reboundsOffensive": 3, "reboundsDefensive": 1, "reboundsTotal": 4, "assists": 2, "steals": 2, "blocks": 1, "turnovers": 0, "foulsPersonal": 5, "points": 6, "plusMinusPoints": 5.0}}, {"personId": 2052, "firstName": "DeShawn", "familyName": "Stevenson", "nameI": "D. Stevenson", "playerSlug": "deshawn-stevenson", "position": "G", "comment": "", "jerseyNum": "", "statistics": {"minutes": "40:20", "fieldGoalsMade": 4, "fieldGoalsAttempted": 9, "fieldGoalsPercentage": 0.444, "threePointersMade": 0, "threePointersAttempted": 0, "threePointersPercentage": 0.0, "freeThrowsMade": 2, "freeThrowsAttempted": 3, "freeThrowsPercentage": 0.667, "reboundsOffensive": 1, "reboundsDefensive": 1, "reboundsTotal": 2, "assists": 1, "steals": 1, "blocks": 0, "turnovers": 1, "foulsPersonal": 1, "points": 10, "plusMinusPoints": 8.0}}, {"personId": 2749, "firstName": "Jameer", "familyName": "Nelson", "nameI": "J. Nelson", "playerSlug": "jameer-nelson", "position": "G", "comment": "", "jerseyNum": "", "statistics": {"minutes": "35:32", "fieldGoalsMade": 8, "fieldGoalsAttempted": 17, "fieldGoalsPercentage": 0.471, "threePointersMade": 1, "threePointersAttempted": 2, "threePointersPercentage": 0.5, "freeThrowsMade": 2, "freeThrowsAttempted": 2, "freeThrowsPercentage": 1.0, "reboundsOffensive": 0, "reboundsDefensive": 7, "reboundsTotal": 7, "assists": 8, "steals": 2, "blocks": 0, "turnovers": 3, "foulsPersonal": 3, "points": 19, "plusMinusPoints": 9.0}}, {"personId": 2545, "firstName": "Darko", "familyName": "Milicic", "nameI": "D. Milicic", "playerSlug": "darko-milicic", "position": "G", "comment": "", "jerseyNum": "", "statistics": {"minutes": "27:37", "fieldGoalsMade": 5, "fieldGoalsAttempted": 9, "fieldGoalsPercentage": 0.556, "threePointersMade": 0, "threePointersAttempted": 0, "threePointersPercentage": 0.0, "freeThrowsMade": 4, "freeThrowsAttempted": 4, "freeThrowsPercentage": 1.0, "reboundsOffensive": 3, "reboundsDefensive": 4, "reboundsTotal": 7, "assists": 0, "steals": 1, "blocks": 3, "turnovers": 1, "foulsPersonal": 2, "points": 14, "plusMinusPoints": 6.0}}, {"personId": 2039, "firstName": "Keyon", "familyName": "Dooling", "nameI": "K. Dooling", "playerSlug": "keyon-dooling", "position": "F", "comment": "", "jerseyNum": "", "statistics": {"minutes": "20:08", "fieldGoalsMade": 3, "fieldGoalsAttempted": 6, "fieldGoalsPercentage": 0.5, "threePointersMade": 0, "threePointersAttempted": 1, "threePointersPercentage": 0.0, "freeThrowsMade": 0, "freeThrowsAttempted": 0, "freeThrowsPercentage": 0.0, "reboundsOffensive": 0, "reboundsDefensive": 0, "reboundsTotal": 0, "assists": 2, "steals": 0, "blocks": 0, "turnovers": 1, "foulsPersonal": 0, "points": 6, "plusMinusPoints": 7.0}}, {"personId": 2772, "firstName": "Trevor", "familyName": "Ariza", "nameI": "T. Ariza", "playerSlug": "trevor-ariza", "position": "F", "comment": "", "jerseyNum": "", "statistics": {"minutes": "12:07", "fieldGoalsMade": 0, "fieldGoalsAttempted": 1, "fieldGoalsPercentage": 0.0, "threePointersMade": 0, "threePointersAttempted": 0, "threePointersPercentage": 0.0, "freeThrowsMade": 0, "freeThrowsAttempted": 0, "freeThrowsPercentage": 0.0, "reboundsOffensive": 0, "reboundsDefensive": 2, "reboundsTotal": 2, "assists": 0, "steals": 1, "blocks": 0, "turnovers": 0, "foulsPersonal": 1, "points": 0, "plusMinusPoints": 2.0}}, {"personId": 278, "firstName": "Stacey", "familyName": "Augmon", "nameI": "S. Augmon", "playerSlug": "stacey-augmon", "position": "", "comment": "DNP - Coach's Decision", "jerseyNum": "", "statistics": {"minutes": "", "fieldGoalsMade": 0, "fieldGoalsAttempted": 0, "fieldGoalsPercentage": 0.0, "threePointersMade": 0, "threePointersAttempted": 0, "threePointersPercentage": 0.0, "freeThrowsMade": 0, "freeThrowsAttempted": 0, "freeThrowsPercentage": 0.0, "reboundsOffensive": 0, "reboundsDefensive": 0, "reboundsTotal": 0, "assists": 0, "steals": 0, "blocks": 0, "turnovers": 0, "foulsPersonal": 0, "points": 0, "plusMinusPoints": 0.0}}, {"personId": 101143, "firstName": "Travis", "familyName": "Diener", "nameI": "T. Diener", "playerSlug": "travis-diener", "position": "", "comment": "DNP - Coach's Decision", "jerseyNum": "", "statistics": {"minutes": "", "fieldGoalsMade": 0, "fieldGoalsAttempted": 0, "fieldGoalsPercentage": 0.0, "threePointersMade": 0, "threePointersAttempted": 0, "threePointersPercentage": 0.0, "freeThrowsMade": 0, "freeThrowsAttempted": 0, "freeThrowsPercentage": 0.0, "reboundsOffensive": 0, "reboundsDefensive": 0, "reboundsTotal": 0, "assists": 0, "steals": 0, "blocks": 0, "turnovers": 0, "foulsPersonal": 0, "points": 0, "plusMinusPoints": 0.0}}, {"personId": 1727, "firstName": "Pat", "familyName": "Garrity", "nameI": "P. Garrity", "playerSlug": "pat-garrity", "position": "", "comment": "DNP - Coach's Decision", "jerseyNum": "", "statistics": {"minutes": "", "fieldGoalsMade": 0, "fieldGoalsAttempted": 0, "fieldGoalsPercentage": 0.0, "threePointersMade": 0, "threePointersAttempted": 0, "threePointersPercentage": 0.0, "freeThrowsMade": 0, "freeThrowsAttempted": 0, "freeThrowsPercentage": 0.0, "reboundsOffensive": 0, "reboundsDefensive": 0, "reboundsTotal": 0, "assists": 0, "steals": 0, "blocks": 0, "turnovers": 0, "foulsPersonal": 0, "points": 0, "plusMinusPoints": 0.0}}, {"personId": 448, "firstName": "Bo", "familyName": "Outlaw", "nameI": "B. Outlaw", "playerSlug": "bo-outlaw", "position": "", "comment": "DNP - Coach's Decision", "jerseyNum": "", "statistics": {"minutes": "", "fieldGoalsMade": 0, "fieldGoalsAttempted": 0, "fieldGoalsPercentage": 0.0, "threePointersMade": 0, "threePointersAttempted": 0, "threePointersPercentage": 0.0, "freeThrowsMade": 0, "freeThrowsAttempted": 0, "freeThrowsPercentage": 0.0, "reboundsOffensive": 0, "reboundsDefensive": 0, "reboundsTotal": 0, "assists": 0, "steals": 0, "blocks": 0, "turnovers": 0, "foulsPersonal": 0, "points": 0, "plusMinusPoints": 0.0}}], "statistics": {"minutes": "240:00", "fieldGoalsMade": 38, "fieldGoalsAttempted": 77, "fieldGoalsPercentage": 0.494, "threePointersMade": 2, "threePointersAttempted": 4, "threePointersPercentage": 0.5, "freeThrowsMade": 14, "freeThrowsAttempted": 19, "freeThrowsPercentage": 0.737, "reboundsOffensive": 10, "reboundsDefensive": 29, "reboundsTotal": 39, "assists": 15, "steals": 9, "blocks": 5, "turnovers": 9, "foulsPersonal": 16, "points": 92, "plusMinusPoints": 12.0}, "starters": {"minutes": "180:08", "fieldGoalsMade": 30, "fieldGoalsAttempted": 61, "fieldGoalsPercentage": 0.492, "threePointersMade": 2, "threePointersAttempted": 3, "threePointersPercentage": 0.667, "freeThrowsMade": 10, "freeThrowsAttempted": 15, "freeThrowsPercentage": 0.667, "reboundsOffensive": 7, "reboundsDefensive": 23, "reboundsTotal": 30, "assists": 13, "steals": 7, "blocks": 2, "turnovers": 7, "foulsPersonal": 13, "points": 72}, "bench": {"minutes": "180:08", "fieldGoalsMade": 8, "fieldGoalsAttempted": 16, "fieldGoalsPercentage": 0.5, "threePointersMade": 0, "threePointersAttempted": 1, "threePointersPercentage": 0.0, "freeThrowsMade": 4, "freeThrowsAttempted": 4, "freeThrowsPercentage": 1.0, "reboundsOffensive": 3, "reboundsDefensive": 6, "reboundsTotal": 9, "assists": 2, "steals": 2, "blocks": 3, "turnovers": 2, "foulsPersonal": 3, "points": 20}}}}