{"meta": {"version": 1, "request": "http://nba.cloud/games/0022300465/boxscoreusage?Format=json", "time": "2026-07-23T18:56:42.5642Z"}, "boxScoreUsage": {"gameId": "0022300465", "awayTeamId": 1610612764, "homeTeamId": 1610612739, "homeTeam": {"teamId": 1610612739, "teamCity": "Cleveland", "teamName": "Cavaliers", "teamTricode": "CLE", "teamSlug": "cavaliers", "players": [{"personId": 1630171, "firstName": "Isaac", "familyName": "Okoro", "nameI": "I. Okoro", "playerSlug": "isaac-okoro", "position": "F", "comment": "", "jerseyNum": "", "statistics": {"minutes": "19:30", "usagePercentage": 0.087, "percentageFieldGoalsMade": 0.19, "percentageFieldGoalsAttempted": 0.108, "percentageThreePointersMade": 0.091, "percentageThreePointersAttempted": 0.056, "percentageFreeThrowsMade": 0.0, "percentageFreeThrowsAttempted": 0.0, "percentageReboundsOffensive": 0.0, "percentageReboundsDefensive": 0.143, "percentageReboundsTotal": 0.118, "percentageAssists": 0.2, "percentageTurnovers": 0.0, "percentageSteals": 0.25, "percentageBlocks": 0.0, "percentageBlocksAllowed": 0.0, "percentagePersonalFouls": 0.333, "percentagePersonalFoulsDrawn": 0.0, "percentagePoints": 0.153}}, {"personId": 1629731, "firstName": "Dean", "familyName": "Wade", "nameI": "D. Wade", "playerSlug": "dean-wade", "position": "F", "comment": "", "jerseyNum": "", "statistics": {"minutes": "20:06", "usagePercentage": 0.065, "percentageFieldGoalsMade": 0.048, "percentageFieldGoalsAttempted": 0.081, "percentageThreePointersMade": 0.0, "percentageThreePointersAttempted": 0.059, "percentageFreeThrowsMade": 0.0, "percentageFreeThrowsAttempted": 0.0, "percentageReboundsOffensive": 0.0, "percentageReboundsDefensive": 0.2, "percentageReboundsTotal": 0.158, "percentageAssists": 0.063, "percentageTurnovers": 0.0, "percentageSteals": 0.0, "percentageBlocks": 0.0, "percentageBlocksAllowed": 0.0, "percentagePersonalFouls": 0.2, "percentagePersonalFoulsDrawn": 0.0, "percentagePoints": 0.032}}, {"personId": 1628386, "firstName": "Jarrett", "familyName": "Allen", "nameI": "J. Allen", "playerSlug": "jarrett-allen", "position": "C", "comment": "", "jerseyNum": "", "statistics": {"minutes": "29:26", "usagePercentage": 0.173, "percentageFieldGoalsMade": 0.219, "percentageFieldGoalsAttempted": 0.156, "percentageThreePointersMade": 0.0, "percentageThreePointersAttempted": 0.0, "percentageFreeThrowsMade": 0.333, "percentageFreeThrowsAttempted": 0.4, "percentageReboundsOffensive": 0.583, "percentageReboundsDefensive": 0.48, "percentageReboundsTotal": 0.514, "percentageAssists": 0.318, "percentageTurnovers": 0.2, "percentageSteals": 0.0, "percentageBlocks": 0.333, "percentageBlocksAllowed": 0.0, "percentagePersonalFouls": 0.0, "percentagePersonalFoulsDrawn": 0.333, "percentagePoints": 0.198}}, {"personId": 1629622, "firstName": "Max", "familyName": "Strus", "nameI": "M. Strus", "playerSlug": "max-strus", "position": "G", "comment": "", "jerseyNum": "", "statistics": {"minutes": "28:01", "usagePercentage": 0.194, "percentageFieldGoalsMade": 0.281, "percentageFieldGoalsAttempted": 0.206, "percentageThreePointersMade": 0.429, "percentageThreePointersAttempted": 0.267, "percentageFreeThrowsMade": 0.0, "percentageFreeThrowsAttempted": 0.0, "percentageReboundsOffensive": 0.154, "percentageReboundsDefensive": 0.077, "percentageReboundsTotal": 0.103, "percentageAssists": 0.136, "percentageTurnovers": 0.25, "percentageSteals": 0.333, "percentageBlocks": 0.167, "percentageBlocksAllowed": 0.333, "percentagePersonalFouls": 0.5, "percentagePersonalFoulsDrawn": 0.125, "percentagePoints": 0.279}}, {"personId": 1628378, "firstName": "Donovan", "familyName": "Mitchell", "nameI": "D. Mitchell", "playerSlug": "donovan-mitchell", "position": "G", "comment": "", "jerseyNum": "", "statistics": {"minutes": "24:15", "usagePercentage": 0.368, "percentageFieldGoalsMade": 0.231, "percentageFieldGoalsAttempted": 0.34, "percentageThreePointersMade": 0.364, "percentageThreePointersAttempted": 0.5, "percentageFreeThrowsMade": 0.667, "percentageFreeThrowsAttempted": 0.6, "percentageReboundsOffensive": 0.2, "percentageReboundsDefensive": 0.105, "percentageReboundsTotal": 0.125, "percentageAssists": 0.222, "percentageTurnovers": 0.4, "percentageSteals": 0.5, "percentageBlocks": 0.5, "percentageBlocksAllowed": 0.5, "percentagePersonalFouls": 0.0, "percentagePersonalFoulsDrawn": 0.5, "percentagePoints": 0.306}}, {"personId": 1630241, "firstName": "Sam", "familyName": "Merrill", "nameI": "S. Merrill", "playerSlug": "sam-merrill", "position": "", "comment": "", "jerseyNum": "", "statistics": {"minutes": "28:32", "usagePercentage": 0.141, "percentageFieldGoalsMade": 0.121, "percentageFieldGoalsAttempted": 0.172, "percentageThreePointersMade": 0.333, "percentageThreePointersAttempted": 0.36, "percentageFreeThrowsMade": 0.0, "percentageFreeThrowsAttempted": 0.0, "percentageReboundsOffensive": 0.067, "percentageReboundsDefensive": 0.133, "percentageReboundsTotal": 0.111, "percentageAssists": 0.273, "percentageTurnovers": 0.0, "percentageSteals": 0.0, "percentageBlocks": 0.0, "percentageBlocksAllowed": 0.0, "percentagePersonalFouls": 0.286, "percentagePersonalFoulsDrawn": 0.1, "percentagePoints": 0.136}}, {"personId": 1627777, "firstName": "Georges", "familyName": "Niang", "nameI": "G. Niang", "playerSlug": "georges-niang", "position": "", "comment": "", "jerseyNum": "", "statistics": {"minutes": "27:54", "usagePercentage": 0.16, "percentageFieldGoalsMade": 0.152, "percentageFieldGoalsAttempted": 0.175, "percentageThreePointersMade": 0.333, "percentageThreePointersAttempted": 0.28, "percentageFreeThrowsMade": 0.667, "percentageFreeThrowsAttempted": 0.333, "percentageReboundsOffensive": 0.071, "percentageReboundsDefensive": 0.241, "percentageReboundsTotal": 0.186, "percentageAssists": 0.048, "percentageTurnovers": 0.0, "percentageSteals": 0.0, "percentageBlocks": 0.0, "percentageBlocksAllowed": 0.5, "percentagePersonalFouls": 0.25, "percentagePersonalFoulsDrawn": 0.125, "percentagePoints": 0.192}}, {"personId": 1627747, "firstName": "Caris", "familyName": "LeVert", "nameI": "C. LeVert", "playerSlug": "caris-levert", "position": "", "comment": "", "jerseyNum": "", "statistics": {"minutes": "22:54", "usagePercentage": 0.286, "percentageFieldGoalsMade": 0.321, "percentageFieldGoalsAttempted": 0.333, "percentageThreePointersMade": 0.333, "percentageThreePointersAttempted": 0.273, "percentageFreeThrowsMade": 0.0, "percentageFreeThrowsAttempted": 0.0, "percentageReboundsOffensive": 0.143, "percentageReboundsDefensive": 0.13, "percentageReboundsTotal": 0.135, "percentageAssists": 0.278, "percentageTurnovers": 0.0, "percentageSteals": 0.5, "percentageBlocks": 0.333, "percentageBlocksAllowed": 0.0, "percentagePersonalFouls": 0.167, "percentagePersonalFoulsDrawn": 0.0, "percentagePoints": 0.3}}, {"personId": 1641854, "firstName": "Craig", "familyName": "Porter Jr.", "nameI": "C. Porter Jr.", "playerSlug": "craig-porter-jr", "position": "", "comment": "", "jerseyNum": "", "statistics": {"minutes": "14:37", "usagePercentage": 0.176, "percentageFieldGoalsMade": 0.235, "percentageFieldGoalsAttempted": 0.192, "percentageThreePointersMade": 0.0, "percentageThreePointersAttempted": 0.0, "percentageFreeThrowsMade": 0.0, "percentageFreeThrowsAttempted": 0.25, "percentageReboundsOffensive": 0.333, "percentageReboundsDefensive": 0.143, "percentageReboundsTotal": 0.176, "percentageAssists": 0.25, "percentageTurnovers": 0.167, "percentageSteals": 0.0, "percentageBlocks": 0.0, "percentageBlocksAllowed": 0.0, "percentagePersonalFouls": 0.0, "percentagePersonalFoulsDrawn": 0.333, "percentagePoints": 0.195}}, {"personId": 202684, "firstName": "Tristan", "familyName": "Thompson", "nameI": "T. Thompson", "playerSlug": "tristan-thompson", "position": "", "comment": "", "jerseyNum": "", "statistics": {"minutes": "18:34", "usagePercentage": 0.213, "percentageFieldGoalsMade": 0.136, "percentageFieldGoalsAttempted": 0.167, "percentageThreePointersMade": 0.0, "percentageThreePointersAttempted": 0.0, "percentageFreeThrowsMade": 0.333, "percentageFreeThrowsAttempted": 0.5, "percentageReboundsOffensive": 0.5, "percentageReboundsDefensive": 0.316, "percentageReboundsTotal": 0.36, "percentageAssists": 0.267, "percentageTurnovers": 0.5, "percentageSteals": 0.0, "percentageBlocks": 0.5, "percentageBlocksAllowed": 1.0, "percentagePersonalFouls": 0.167, "percentagePersonalFoulsDrawn": 0.6, "percentagePoints": 0.13}}, {"personId": 1627745, "firstName": "Damian", "familyName": "Jones", "nameI": "D. Jones", "playerSlug": "damian-jones", "position": "", "comment": "", "jerseyNum": "", "statistics": {"minutes": "6:11", "usagePercentage": 0.214, "percentageFieldGoalsMade": 0.4, "percentageFieldGoalsAttempted": 0.333, "percentageThreePointersMade": 0.0, "percentageThreePointersAttempted": 0.5, "percentageFreeThrowsMade": 0.0, "percentageFreeThrowsAttempted": 0.0, "percentageReboundsOffensive": 0.0, "percentageReboundsDefensive": 0.167, "percentageReboundsTotal": 0.143, "percentageAssists": 0.0, "percentageTurnovers": 0.0, "percentageSteals": 0.0, "percentageBlocks": 1.0, "percentageBlocksAllowed": 0.0, "percentagePersonalFouls": 0.0, "percentagePersonalFoulsDrawn": 0.0, "percentagePoints": 0.364}}, {"personId": 1629660, "firstName": "Ty", "familyName": "Jerome", "nameI": "T. Jerome", "playerSlug": "ty-jerome", "position": "", "comment": "DND - Injury/Illness", "jerseyNum": "", "statistics": {"minutes": "", "usagePercentage": 0.0, "percentageFieldGoalsMade": 0.0, "percentageFieldGoalsAttempted": 0.0, "percentageThreePointersMade": 0.0, "percentageThreePointersAttempted": 0.0, "percentageFreeThrowsMade": 0.0, "percentageFreeThrowsAttempted": 0.0, "percentageReboundsOffensive": 0.0, "percentageReboundsDefensive": 0.0, "percentageReboundsTotal": 0.0, "percentageAssists": 0.0, "percentageTurnovers": 0.0, "percentageSteals": 0.0, "percentageBlocks": 0.0, "percentageBlocksAllowed": 0.0, "percentagePersonalFouls": 0.0, "percentagePersonalFoulsDrawn": 0.0, "percentagePoints": 0.0}}], "statistics": {"minutes": "240:00", "usagePercentage": 1.0, "percentageFieldGoalsMade": 1.0, "percentageFieldGoalsAttempted": 1.0, "percentageThreePointersMade": 1.0, "percentageThreePointersAttempted": 1.0, "percentageFreeThrowsMade": 1.0, "percentageFreeThrowsAttempted": 1.0, "percentageReboundsOffensive": 1.0, "percentageReboundsDefensive": 1.0, "percentageReboundsTotal": 1.0, "percentageAssists": 1.0, "percentageTurnovers": 1.0, "percentageSteals": 1.0, "percentageBlocks": 1.0, "percentageBlocksAllowed": 1.0, "percentagePersonalFouls": 1.0, "percentagePersonalFoulsDrawn": 1.0, "percentagePoints": 1.0}}, "awayTeam": {"teamId": 1610612764, "teamCity": "Washington", "teamName": "Wizards", "teamTricode": "WAS", "teamSlug": "wizards", "players": [{"personId": 1630166, "firstName": "Deni", "familyName": "Avdija", "nameI": "D. Avdija", "playerSlug": "deni-avdija", "position": "F", "comment": "", "jerseyNum": "", "statistics": {"minutes": "21:28", "usagePercentage": 0.255, "percentageFieldGoalsMade": 0.15, "percentageFieldGoalsAttempted": 0.229, "percentageThreePointersMade": 0.2, "percentageThreePointersAttempted": 0.188, "percentageFreeThrowsMade": 0.0, "percentageFreeThrowsAttempted": 0.0, "percentageReboundsOffensive": 0.25, "percentageReboundsDefensive": 0.333, "percentageReboundsTotal": 0.3, "percentageAssists": 0.444, "percentageTurnovers": 0.6, "percentageSteals": 0.333, "percentageBlocks": 0.0, "percentageBlocksAllowed": 0.25, "percentagePersonalFouls": 0.25, "percentagePersonalFoulsDrawn": 0.5, "percentagePoints": 0.156}}, {"personId": 1628398, "firstName": "Kyle", "familyName": "Kuzma", "nameI": "K. Kuzma", "playerSlug": "kyle-kuzma", "position": "F", "comment": "", "jerseyNum": "", "statistics": {"minutes": "22:42", "usagePercentage": 0.224, "percentageFieldGoalsMade": 0.318, "percentageFieldGoalsAttempted": 0.235, "percentageThreePointersMade": 0.333, "percentageThreePointersAttempted": 0.4, "percentageFreeThrowsMade": 0.0, "percentageFreeThrowsAttempted": 0.0, "percentageReboundsOffensive": 0.0, "percentageReboundsDefensive": 0.2, "percentageReboundsTotal": 0.111, "percentageAssists": 0.273, "percentageTurnovers": 0.2, "percentageSteals": 0.333, "percentageBlocks": 0.0, "percentageBlocksAllowed": 0.0, "percentagePersonalFouls": 0.143, "percentagePersonalFoulsDrawn": 0.0, "percentagePoints": 0.32}}, {"personId": 1629655, "firstName": "Daniel", "familyName": "Gafford", "nameI": "D. Gafford", "playerSlug": "daniel-gafford", "position": "C", "comment": "", "jerseyNum": "", "statistics": {"minutes": "20:11", "usagePercentage": 0.154, "percentageFieldGoalsMade": 0.286, "percentageFieldGoalsAttempted": 0.178, "percentageThreePointersMade": 0.0, "percentageThreePointersAttempted": 0.0, "percentageFreeThrowsMade": 0.0, "percentageFreeThrowsAttempted": 0.333, "percentageReboundsOffensive": 0.375, "percentageReboundsDefensive": 0.182, "percentageReboundsTotal": 0.263, "percentageAssists": 0.111, "percentageTurnovers": 0.0, "percentageSteals": 0.0, "percentageBlocks": 0.5, "percentageBlocksAllowed": 0.5, "percentagePersonalFouls": 0.333, "percentagePersonalFoulsDrawn": 0.333, "percentagePoints": 0.261}}, {"personId": 1629673, "firstName": "Jordan", "familyName": "Poole", "nameI": "J. Poole", "playerSlug": "jordan-poole", "position": "G", "comment": "", "jerseyNum": "", "statistics": {"minutes": "22:42", "usagePercentage": 0.207, "percentageFieldGoalsMade": 0.136, "percentageFieldGoalsAttempted": 0.216, "percentageThreePointersMade": 0.333, "percentageThreePointersAttempted": 0.267, "percentageFreeThrowsMade": 0.0, "percentageFreeThrowsAttempted": 0.0, "percentageReboundsOffensive": 0.375, "percentageReboundsDefensive": 0.0, "percentageReboundsTotal": 0.167, "percentageAssists": 0.182, "percentageTurnovers": 0.2, "percentageSteals": 0.0, "percentageBlocks": 0.0, "percentageBlocksAllowed": 0.4, "percentagePersonalFouls": 0.429, "percentagePersonalFoulsDrawn": 0.25, "percentagePoints": 0.16}}, {"personId": 1626145, "firstName": "Tyus", "familyName": "Jones", "nameI": "T. Jones", "playerSlug": "tyus-jones", "position": "G", "comment": "", "jerseyNum": "", "statistics": {"minutes": "20:49", "usagePercentage": 0.208, "percentageFieldGoalsMade": 0.182, "percentageFieldGoalsAttempted": 0.234, "percentageThreePointersMade": 0.167, "percentageThreePointersAttempted": 0.143, "percentageFreeThrowsMade": 0.0, "percentageFreeThrowsAttempted": 0.0, "percentageReboundsOffensive": 0.0, "percentageReboundsDefensive": 0.2, "percentageReboundsTotal": 0.111, "percentageAssists": 0.2, "percentageTurnovers": 0.0, "percentageSteals": 0.333, "percentageBlocks": 0.5, "percentageBlocksAllowed": 0.0, "percentagePersonalFouls": 0.0, "percentagePersonalFoulsDrawn": 0.0, "percentagePoints": 0.18}}, {"personId": 1641731, "firstName": "Bilal", "familyName": "Coulibaly", "nameI": "B. Coulibaly", "playerSlug": "bilal-coulibaly", "position": "", "comment": "", "jerseyNum": "", "statistics": {"minutes": "32:33", "usagePercentage": 0.2, "percentageFieldGoalsMade": 0.077, "percentageFieldGoalsAttempted": 0.182, "percentageThreePointersMade": 0.111, "percentageThreePointersAttempted": 0.154, "percentageFreeThrowsMade": 0.0, "percentageFreeThrowsAttempted": 0.2, "percentageReboundsOffensive": 0.2, "percentageReboundsDefensive": 0.25, "percentageReboundsTotal": 0.238, "percentageAssists": 0.059, "percentageTurnovers": 0.5, "percentageSteals": 0.5, "percentageBlocks": 0.667, "percentageBlocksAllowed": 0.2, "percentagePersonalFouls": 0.364, "percentagePersonalFoulsDrawn": 0.1, "percentagePoints": 0.076}}, {"personId": 1626153, "firstName": "Delon", "familyName": "Wright", "nameI": "D. Wright", "playerSlug": "delon-wright", "position": "", "comment": "", "jerseyNum": "", "statistics": {"minutes": "18:26", "usagePercentage": 0.093, "percentageFieldGoalsMade": 0.0, "percentageFieldGoalsAttempted": 0.083, "percentageThreePointersMade": 0.0, "percentageThreePointersAttempted": 0.071, "percentageFreeThrowsMade": 0.0, "percentageFreeThrowsAttempted": 0.0, "percentageReboundsOffensive": 0.0, "percentageReboundsDefensive": 0.2, "percentageReboundsTotal": 0.154, "percentageAssists": 0.4, "percentageTurnovers": 0.25, "percentageSteals": 0.333, "percentageBlocks": 0.333, "percentageBlocksAllowed": 0.0, "percentagePersonalFouls": 0.25, "percentagePersonalFoulsDrawn": 0.25, "percentagePoints": 0.0}}, {"personId": 203488, "firstName": "Mike", "familyName": "Muscala", "nameI": "M. Muscala", "playerSlug": "mike-muscala", "position": "", "comment": "", "jerseyNum": "", "statistics": {"minutes": "20:54", "usagePercentage": 0.188, "percentageFieldGoalsMade": 0.313, "percentageFieldGoalsAttempted": 0.209, "percentageThreePointersMade": 0.286, "percentageThreePointersAttempted": 0.25, "percentageFreeThrowsMade": 0.0, "percentageFreeThrowsAttempted": 0.0, "percentageReboundsOffensive": 0.667, "percentageReboundsDefensive": 0.2, "percentageReboundsTotal": 0.308, "percentageAssists": 0.231, "percentageTurnovers": 0.0, "percentageSteals": 0.0, "percentageBlocks": 0.0, "percentageBlocksAllowed": 0.0, "percentagePersonalFouls": 0.0, "percentagePersonalFoulsDrawn": 0.0, "percentagePoints": 0.293}}, {"personId": 1630557, "firstName": "Corey", "familyName": "Kispert", "nameI": "C. Kispert", "playerSlug": "corey-kispert", "position": "", "comment": "", "jerseyNum": "", "statistics": {"minutes": "19:39", "usagePercentage": 0.239, "percentageFieldGoalsMade": 0.267, "percentageFieldGoalsAttempted": 0.231, "percentageThreePointersMade": 0.0, "percentageThreePointersAttempted": 0.278, "percentageFreeThrowsMade": 0.8, "percentageFreeThrowsAttempted": 0.6, "percentageReboundsOffensive": 0.0, "percentageReboundsDefensive": 0.1, "percentageReboundsTotal": 0.071, "percentageAssists": 0.0, "percentageTurnovers": 0.0, "percentageSteals": 0.0, "percentageBlocks": 0.0, "percentageBlocksAllowed": 0.0, "percentagePersonalFouls": 0.0, "percentagePersonalFoulsDrawn": 0.625, "percentagePoints": 0.3}}, {"personId": 1629013, "firstName": "Landry", "familyName": "Shamet", "nameI": "L. Shamet", "playerSlug": "landry-shamet", "position": "", "comment": "", "jerseyNum": "", "statistics": {"minutes": "15:08", "usagePercentage": 0.194, "percentageFieldGoalsMade": 0.231, "percentageFieldGoalsAttempted": 0.207, "percentageThreePointersMade": 0.667, "percentageThreePointersAttempted": 0.3, "percentageFreeThrowsMade": 0.2, "percentageFreeThrowsAttempted": 0.2, "percentageReboundsOffensive": 0.0, "percentageReboundsDefensive": 0.375, "percentageReboundsTotal": 0.273, "percentageAssists": 0.25, "percentageTurnovers": 0.0, "percentageSteals": 0.25, "percentageBlocks": 0.0, "percentageBlocksAllowed": 1.0, "percentagePersonalFouls": 0.0, "percentagePersonalFoulsDrawn": 0.111, "percentagePoints": 0.265}}, {"personId": 1630215, "firstName": "Jared", "familyName": "Butler", "nameI": "J. Butler", "playerSlug": "jared-butler", "position": "", "comment": "", "jerseyNum": "", "statistics": {"minutes": "8:45", "usagePercentage": 0.1, "percentageFieldGoalsMade": 0.286, "percentageFieldGoalsAttempted": 0.111, "percentageThreePointersMade": 0.5, "percentageThreePointersAttempted": 0.143, "percentageFreeThrowsMade": 0.0, "percentageFreeThrowsAttempted": 0.0, "percentageReboundsOffensive": 0.0, "percentageReboundsDefensive": 0.25, "percentageReboundsTotal": 0.2, "percentageAssists": 0.333, "percentageTurnovers": 0.0, "percentageSteals": 0.0, "percentageBlocks": 0.0, "percentageBlocksAllowed": 0.0, "percentagePersonalFouls": 0.0, "percentagePersonalFoulsDrawn": 0.0, "percentagePoints": 0.25}}, {"personId": 1630647, "firstName": "Eugene", "familyName": "Omoruyi", "nameI": "E. Omoruyi", "playerSlug": "eugene-omoruyi", "position": "", "comment": "", "jerseyNum": "", "statistics": {"minutes": "6:55", "usagePercentage": 0.2, "percentageFieldGoalsMade": 0.2, "percentageFieldGoalsAttempted": 0.231, "percentageThreePointersMade": 0.0, "percentageThreePointersAttempted": 0.25, "percentageFreeThrowsMade": 0.0, "percentageFreeThrowsAttempted": 0.0, "percentageReboundsOffensive": 1.0, "percentageReboundsDefensive": 0.0, "percentageReboundsTotal": 0.25, "percentageAssists": 0.0, "percentageTurnovers": 0.0, "percentageSteals": 0.0, "percentageBlocks": 0.0, "percentageBlocksAllowed": 1.0, "percentagePersonalFouls": 1.0, "percentagePersonalFoulsDrawn": 0.0, "percentagePoints": 0.143}}, {"personId": 1631098, "firstName": "Johnny", "familyName": "Davis", "nameI": "J. Davis", "playerSlug": "johnny-davis", "position": "", "comment": "", "jerseyNum": "", "statistics": {"minutes": "5:13", "usagePercentage": 0.3, "percentageFieldGoalsMade": 0.25, "percentageFieldGoalsAttempted": 0.3, "percentageThreePointersMade": 0.0, "percentageThreePointersAttempted": 0.0, "percentageFreeThrowsMade": 0.0, "percentageFreeThrowsAttempted": 0.0, "percentageReboundsOffensive": 0.0, "percentageReboundsDefensive": 0.0, "percentageReboundsTotal": 0.0, "percentageAssists": 0.0, "percentageTurnovers": 0.0, "percentageSteals": 0.0, "percentageBlocks": 0.0, "percentageBlocksAllowed": 0.0, "percentagePersonalFouls": 0.0, "percentagePersonalFoulsDrawn": 0.0, "percentagePoints": 0.222}}, {"personId": 1630264, "firstName": "Anthony", "familyName": "Gill", "nameI": "A. Gill", "playerSlug": "anthony-gill", "position": "", "comment": "", "jerseyNum": "", "statistics": {"minutes": "4:35", "usagePercentage": 0.111, "percentageFieldGoalsMade": 0.25, "percentageFieldGoalsAttempted": 0.111, "percentageThreePointersMade": 0.0, "percentageThreePointersAttempted": 0.0, "percentageFreeThrowsMade": 0.0, "percentageFreeThrowsAttempted": 0.0, "percentageReboundsOffensive": 0.0, "percentageReboundsDefensive": 0.333, "percentageReboundsTotal": 0.333, "percentageAssists": 0.0, "percentageTurnovers": 0.0, "percentageSteals": 0.0, "percentageBlocks": 0.0, "percentageBlocksAllowed": 0.0, "percentagePersonalFouls": 0.0, "percentagePersonalFoulsDrawn": 0.0, "percentagePoints": 0.222}}, {"personId": 201568, "firstName": "Danilo", "familyName": "Gallinari", "nameI": "D. Gallinari", "playerSlug": "danilo-gallinari", "position": "", "comment": "DNP - Coach's Decision", "jerseyNum": "", "statistics": {"minutes": "", "usagePercentage": 0.0, "percentageFieldGoalsMade": 0.0, "percentageFieldGoalsAttempted": 0.0, "percentageThreePointersMade": 0.0, "percentageThreePointersAttempted": 0.0, "percentageFreeThrowsMade": 0.0, "percentageFreeThrowsAttempted": 0.0, "percentageReboundsOffensive": 0.0, "percentageReboundsDefensive": 0.0, "percentageReboundsTotal": 0.0, "percentageAssists": 0.0, "percentageTurnovers": 0.0, "percentageSteals": 0.0, "percentageBlocks": 0.0, "percentageBlocksAllowed": 0.0, "percentagePersonalFouls": 0.0, "percentagePersonalFoulsDrawn": 0.0, "percentagePoints": 0.0}}], "statistics": {"minutes": "240:00", "usagePercentage": 1.0, "percentageFieldGoalsMade": 1.0, "percentageFieldGoalsAttempted": 1.0, "percentageThreePointersMade": 1.0, "percentageThreePointersAttempted": 1.0, "percentageFreeThrowsMade": 1.0, "percentageFreeThrowsAttempted": 1.0, "percentageReboundsOffensive": 1.0, "percentageReboundsDefensive": 1.0, "percentageReboundsTotal": 1.0, "percentageAssists": 1.0, "percentageTurnovers": 1.0, "percentageSteals": 1.0, "percentageBlocks": 1.0, "percentageBlocksAllowed": 1.0, "percentagePersonalFouls": 1.0, "percentagePersonalFoulsDrawn": 1.0, "percentagePoints": 1.0}}}}